verser/__init__.py
verser/__version2__.py
verser/__version__.py
verser/examples.py
verser/main.py
verser/test.py
verser/verser
verser/verserLocal/--__version__.py
verser/verserLocal/__init__.py
verser/verserLocal/__version__.py
verser/verserLocal/tests_main.py
verser/verserLocal/verser_.py
verser/verserLocal/api/__init__.py
verser/verserLocal/api/compat.py
verser/verserLocal/api/pypi_latest.py
verser/verserLocal/api/release.py
verser/verserLocal/common/__init__.py
verser/verserLocal/common/colors.py
verser/verserLocal/common/files.py
verser/verserLocal/components/defaults.py
verser/verserLocal/components/display_version.py
verser/verserLocal/components/increment_functions.py
verser/verserLocal/components/mock_versions.py
verser/verserLocal/components/project.py
verser/verserLocal/components/version_functions.py
verser/verserLocal/components/version_parts.py
verser/verserLocal/config/__init__.py
verser/verserLocal/config/config.py
verser/verserLocal/enums/__init__.py
verser/verserLocal/enums/parts_enum.py
verser/verserLocal/format/__init__.py
verser/verserLocal/format/format_check.py
verser/verserLocal/requests_/__init__.py
verser/verserLocal/requests_/ev_request.py
verser/verserLocal/requests_/my_cache.py
verser/verserLocal/requests_/request_error_classes.py
verser/verserLocal/requests_/requests_.py
verser/verserLocal/requests_/test_reg_result.pickle
verser/verserLocal/state/__init__.py
verser/verserLocal/state/current_state.py
verser/verserLocal/state/test_or_real.py
verser/verserLocal/tests/__init__.py
verser/verserLocal/tests/test_verser.py
verser/verserLocal/utils/__init__.py
verser/verserLocal/utils/utils_general.py
verser-0.1.10.dist-info/LICENSE
verser-0.1.10.dist-info/METADATA
verser-0.1.10.dist-info/WHEEL
verser-0.1.10.dist-info/top_level.txt
verser-0.1.10.dist-info/RECORD
