Metadata-Version: 2.1
Name: verser
Version: 0.1.10
Summary: Generates next version number for your pyton package. If your package is a PYPI package it checks the latest version from PYPI and creates next version depending on your choices. Alternatively you may use local option which reads local __version__.py or any other file name you provide and creates the next version.Creates version file and reads from the same path. It also provides useful functions to show your package's version at run time.
Home-page: 
Author: Sermet Pekin
Author-email: sermet.pekin@gmail.com
License: MIT
Project-URL: Homepage, https://github.com/SermetPekin/verser-repo
Project-URL: Documentation, https://github.com/SermetPekin/verser-repo
Keywords: verser
Requires-Python: >=3
License-File: LICENSE
Requires-Dist: rich
Requires-Dist: requests
Provides-Extra: dev
Provides-Extra: docs
Provides-Extra: testing
